{"Title":"One Piece","Year":"2023\u2013","Rated":"TV-14","Released":"31 Aug 2023","Genre":"Action, Adventure, Comedy","Writer":"Steven Maeda, Matt Owens","Actors":"I\u00F1aki Godoy, Emily Rudd, Mackenyu","Plot":"In a seafaring world, a young pirate captain sets out with his crew to attain the title of Pirate King, and to discover the mythical treasure known as \u0027One Piece.\u0027","Language":"English","Country":"United Kingdom, United States, South Africa, Japan","Poster":"https://m.media-amazon.com/images/M/MV5BYzczMzllN2UtNDJmOS00MmE5LWE2MWYtNGEwODcwMDc2M2YyXkEyXkFqcGdeQXVyMDM2NDM2MQ@@._V1_SX300.jpg","Ratings":[{"Source":"Internet Movie Database","Value":"8.4/10"}],"imdbRating":"8.4","imdbVotes":"129,053","imdbID":"tt11737520","Type":"series","Response":"True"}