{"Title":"One Piece","Year":"2023–","Rated":"TV-14","Released":"31 Aug 2023","Runtime":"","Genre":"Action, Adventure, Comedy","Director":"","Writer":"Steven Maeda, Matt Owens","Actors":"Iñaki Godoy, Emily Rudd, Mackenyu","Plot":"In a seafaring world, a young pirate captain sets out with his crew to attain the title of Pirate King, and to discover the mythical treasure known as 'One Piece.'","Language":"English","Country":"United Kingdom, United States, South Africa, Japan","Awards":"1 win & 5 nominations","Poster":"https://m.media-amazon.com/images/M/MV5BYzczMzllN2UtNDJmOS00MmE5LWE2MWYtNGEwODcwMDc2M2YyXkEyXkFqcGdeQXVyMDM2NDM2MQ@@._V1_SX300.jpg","Ratings":[{"Source":"Internet Movie Database","Value":"8.3/10"}],"Metascore":"","imdbRating":"8.3","imdbVotes":"146,245","imdbID":"tt11737520","Type":"series","totalSeasons":"1","Response":"True"}